coloralf/Color.py
coloralf/__init__.py
coloralf/func.py
coloralf/loc.py
coloralf-0.3.dist-info/METADATA
coloralf-0.3.dist-info/WHEEL
coloralf-0.3.dist-info/top_level.txt
coloralf-0.3.dist-info/RECORD
