Metadata-Version: 2.1
Name: coloralf
Version: 0.3
Summary: Simple package to easy color & transform your console string and output
Author: Aexeos - Angelo LF
Author-email: aexeos413@gmail.com
